envyronment.py
envyronment-0.4.0.dist-info/licenses/LICENSE
envyronment-0.4.0.dist-info/METADATA
envyronment-0.4.0.dist-info/WHEEL
envyronment-0.4.0.dist-info/top_level.txt
envyronment-0.4.0.dist-info/RECORD
