Metadata-Version: 2.4
Name: envyronment
Version: 0.4.0
Summary: A tiny module to read environment variables and tranform them.
Author-email: Sonny Valkeneers <sonny@softllama.net>
License-Expression: MIT
Project-URL: Repository, https://github.com/shifqu/envyronment.git
Project-URL: Issues, https://github.com/shifqu/envyronment/issues
Project-URL: ReleaseNotes, https://github.com/shifqu/envyronment/releases
Project-URL: Funding, https://github.com/sponsors/shifqu
Classifier: Intended Audience :: Developers
Classifier: Operating System :: OS Independent
Classifier: Programming Language :: Python
Classifier: Programming Language :: Python :: 3
Classifier: Programming Language :: Python :: 3 :: Only
Classifier: Programming Language :: Python :: 3.13
Classifier: Topic :: Software Development :: Libraries
Classifier: Topic :: Software Development :: Libraries :: Python Modules
Classifier: Topic :: Utilities
Classifier: Typing :: Typed
Requires-Python: >=3.10
License-File: LICENSE
Provides-Extra: dotenv
Requires-Dist: python-dotenv<2.0,>=1.2; extra == "dotenv"
Provides-Extra: dev
Requires-Dist: coverage>=7.11; extra == "dev"
Requires-Dist: ruff>=0.14; extra == "dev"
Requires-Dist: pylint<4.0; extra == "dev"
Requires-Dist: pyright>=1.1; extra == "dev"
Provides-Extra: build
Requires-Dist: build<2.0,>=1.3; extra == "build"
Requires-Dist: twine<7.0,>=6.2; extra == "build"
Dynamic: license-file
